YouxiBianchengMoshi/README.md
YouxiBianchengMoshi/__init__.py
YouxiBianchengMoshi/__main__.py
YouxiBianchengMoshi/file.epub
YouxiBianchengMoshi/index.html
YouxiBianchengMoshi/css/__init__.py
YouxiBianchengMoshi/css/annotations.css
YouxiBianchengMoshi/css/main.css
YouxiBianchengMoshi/css/normalize.css
YouxiBianchengMoshi/css/popup.css
YouxiBianchengMoshi/font/__init__.py
YouxiBianchengMoshi/font/fontello.eot
YouxiBianchengMoshi/font/fontello.svg
YouxiBianchengMoshi/font/fontello.ttf
YouxiBianchengMoshi/font/fontello.woff
YouxiBianchengMoshi/img/__init__.py
YouxiBianchengMoshi/img/annotator-glyph-sprite.png
YouxiBianchengMoshi/img/annotator-icon-sprite.png
YouxiBianchengMoshi/img/apple-touch-icon.png
YouxiBianchengMoshi/img/cancelfullscreen.png
YouxiBianchengMoshi/img/close.png
YouxiBianchengMoshi/img/fullscreen.png
YouxiBianchengMoshi/img/loader.gif
YouxiBianchengMoshi/img/menu-icon.png
YouxiBianchengMoshi/img/save.png
YouxiBianchengMoshi/img/saved.png
YouxiBianchengMoshi/img/settings-s.png
YouxiBianchengMoshi/img/settings.png
YouxiBianchengMoshi/img/star.png
YouxiBianchengMoshi/js/__init__.py
YouxiBianchengMoshi/js/epub.js
YouxiBianchengMoshi/js/epub.min.js
YouxiBianchengMoshi/js/epub.min.map
YouxiBianchengMoshi/js/hooks.min.js
YouxiBianchengMoshi/js/hooks.min.map
YouxiBianchengMoshi/js/reader.js
YouxiBianchengMoshi/js/reader.js.map
YouxiBianchengMoshi/js/reader.min.js
YouxiBianchengMoshi/js/reader.min.map
YouxiBianchengMoshi/js/hooks/__init__.py
YouxiBianchengMoshi/js/hooks/extensions/__init__.py
YouxiBianchengMoshi/js/hooks/extensions/highlight.js
YouxiBianchengMoshi/js/libs/__init__.py
YouxiBianchengMoshi/js/libs/jquery.min.js
YouxiBianchengMoshi/js/libs/localforage.min.js
YouxiBianchengMoshi/js/libs/screenfull.js
YouxiBianchengMoshi/js/libs/screenfull.min.js
YouxiBianchengMoshi/js/libs/zip.min.js
YouxiBianchengMoshi/js/plugins/__init__.py
YouxiBianchengMoshi/js/plugins/hypothesis.js
YouxiBianchengMoshi/js/plugins/search.js
youxi_biancheng_moshi-2024.3.2.0.dist-info/METADATA
youxi_biancheng_moshi-2024.3.2.0.dist-info/WHEEL
youxi_biancheng_moshi-2024.3.2.0.dist-info/entry_points.txt
youxi_biancheng_moshi-2024.3.2.0.dist-info/top_level.txt
youxi_biancheng_moshi-2024.3.2.0.dist-info/RECORD
